bprc/__init__.py
bprc/__main__.py
bprc/_version.py
bprc/cli.py
bprc/core.py
bprc/outputprocessor.py
bprc/recipe.py
bprc/stepprocessor.py
bprc/utils.py
bprc/variables.py
bprc/varprocessor.py
bprc-0.7.0.dist-info/DESCRIPTION.rst
bprc-0.7.0.dist-info/METADATA
bprc-0.7.0.dist-info/RECORD
bprc-0.7.0.dist-info/WHEEL
bprc-0.7.0.dist-info/entry_points.txt
bprc-0.7.0.dist-info/metadata.json
bprc-0.7.0.dist-info/top_level.txt
tests/__init__.py
tests/test_output.py
tests/test_recipe_prepare_and_parse.py
tests/test_recipe_step_calls.py
tests/test_variable_parser.py
tests/test_yaml_load.py
