Metadata-Version: 2.0
Name: bprc
Version: 0.7.0
Summary: Batch Processing RESTful Client
Home-page: https://github.com/bradwood/BPRC
Author: Bradley Wood
Author-email: github@bradleywood.com
License: MIT
Download-URL: https://github.com/bradwood/BPRC/tarball/0.7.0
Keywords: devops REST json microservices yaml script
Platform: UNKNOWN
Classifier: Development Status :: 4 - Beta
Classifier: Intended Audience :: Developers
Classifier: Intended Audience :: Information Technology
Classifier: Intended Audience :: System Administrators
Classifier: Operating System :: POSIX :: Linux
Classifier: Operating System :: MacOS :: MacOS X
Classifier: Topic :: Software Development :: Build Tools
Classifier: License :: OSI Approved :: MIT License
Classifier: Programming Language :: Python :: 3.5
Classifier: Environment :: Console
Classifier: Environment :: Web Environment
Classifier: Topic :: Utilities
Classifier: Topic :: Internet :: WWW/HTTP
Classifier: Topic :: Internet :: WWW/HTTP :: HTTP Servers
Classifier: Topic :: Internet :: WWW/HTTP :: WSGI
Classifier: Topic :: Internet :: WWW/HTTP :: Browsers
Classifier: Topic :: System :: Installation/Setup
Classifier: Topic :: System :: Systems Administration
Requires-Dist: pygments (>=2.1.3)
Requires-Dist: pyyaml (>=3.11)
Requires-Dist: requests (>=2.10.0)
